cytoolz/_signatures.py
cytoolz/cpython.pxd
cytoolz/functoolz.pyx
cytoolz/utils.pyx
cytoolz/dicttoolz.pxd
cytoolz/functoolz.pxd
cytoolz/itertoolz.pxd
cytoolz/dicttoolz.pyx
cytoolz/utils.pxd
cytoolz/itertoolz.cpython-311-aarch64-linux-gnu.so
cytoolz/recipes.pyx
cytoolz/itertoolz.pyx
cytoolz/__init__.py
cytoolz/compatibility.py
cytoolz/_version.py
cytoolz/dicttoolz.cpython-311-aarch64-linux-gnu.so
cytoolz/recipes.pxd
cytoolz/functoolz.cpython-311-aarch64-linux-gnu.so
cytoolz/utils.cpython-311-aarch64-linux-gnu.so
cytoolz/__init__.pxd
cytoolz/recipes.cpython-311-aarch64-linux-gnu.so
cytoolz/tests/test_dev_skip_test.py
cytoolz/tests/test_docstrings.py
cytoolz/tests/test_functoolz.py
cytoolz/tests/test_curried_toolzlike.py
cytoolz/tests/test_embedded_sigs.py
cytoolz/tests/test_doctests.py
cytoolz/tests/test_utils.py
cytoolz/tests/test_inspect_args.py
cytoolz/tests/dev_skip_test.py
cytoolz/tests/test_serialization.py
cytoolz/tests/test_compatibility.py
cytoolz/tests/test_tlz.py
cytoolz/tests/test_none_safe.py
cytoolz/tests/test_curried.py
cytoolz/tests/test_dicttoolz.py
cytoolz/tests/test_recipes.py
cytoolz/tests/test_signatures.py
cytoolz/tests/test_itertoolz.py
cytoolz/curried/exceptions.py
cytoolz/curried/__init__.py
cytoolz/curried/operator.py
cytoolz-1.0.1.dist-info/top_level.txt
cytoolz-1.0.1.dist-info/RECORD
cytoolz-1.0.1.dist-info/LICENSE.txt
cytoolz-1.0.1.dist-info/AUTHORS.md
cytoolz-1.0.1.dist-info/METADATA
cytoolz-1.0.1.dist-info/WHEEL
