Metadata-Version: 2.1
Name: cytoolz
Version: 1.0.1
Summary: Cython implementation of Toolz: High performance functional utilities
Home-page: https://github.com/pytoolz/cytoolz
Author: https://raw.github.com/pytoolz/cytoolz/master/AUTHORS.md
Author-email: erik.n.welch@gmail.com
Maintainer: Erik Welch
Maintainer-email: erik.n.welch@gmail.com
License: BSD
Keywords: functional utility itertools functools iterator generator curry memoize lazy streaming bigdata cython toolz cytoolz
Platform: UNKNOWN
Classifier: Development Status :: 5 - Production/Stable
Classifier: Intended Audience :: Developers
Classifier: Intended Audience :: Education
Classifier: Intended Audience :: Science/Research
Classifier: License :: OSI Approved :: BSD License
Classifier: Operating System :: OS Independent
Classifier: Programming Language :: Cython
Classifier: Programming Language :: Python
Classifier: Programming Language :: Python :: 3
Classifier: Programming Language :: Python :: 3.8
Classifier: Programming Language :: Python :: 3.9
Classifier: Programming Language :: Python :: 3.10
Classifier: Programming Language :: Python :: 3.11
Classifier: Programming Language :: Python :: 3.12
Classifier: Programming Language :: Python :: 3.13
Classifier: Programming Language :: Python :: Implementation :: CPython
Classifier: Programming Language :: Python :: Implementation :: PyPy
Classifier: Topic :: Scientific/Engineering
Classifier: Topic :: Scientific/Engineering :: Information Analysis
Classifier: Topic :: Software Development
Classifier: Topic :: Software Development :: Libraries
Classifier: Topic :: Software Development :: Libraries :: Python Modules
Classifier: Topic :: Utilities
Requires-Python: >=3.8
Provides-Extra: cython
